{
    "posts":[{"author": "Kuрилл Кирилович",
                "image": "images/kirill.jpeg",
                "title": "Внеземные цивилизации",
                "date": "2010/5/28",
                "text": "Представления о научно-техническом прогрессе дают возможность предположить, что некоторые"
            },{
                "author": "Сергей Кирилович",
                "image": "images/sergey.jpeg",
                "title": "Конференция в честь 150-летия Московского зоопарка",
                "date": "2010/5/28",
                "text": "Мне посчастливилось попасть на пресс-конференцию на тему: 'Проведение Международной конференции в честь 150-летия Московского зоопарка'. На мероприятии также были такие"
            },{
                "author": "Александр Свердлов",
                "image": "images/whoIsIt.jpg",
                "title": "Первый канал это ад на Земле",
                "date": "2010/5/28",
                "text": "Дома я телевизор не смотрю. Да и появился он у меня не так давно. Но пока был на Бали, во время вечеров с поездок по острову, хотелось поваляться в номере, никуда не ходить. Неожиданно нашел кнопку Первого канала на телеке."
            }, {
                "author": "Unknown Unknown",
                "title": "10 задач, которые выполняет российский флот",
                "date": "2010/5/28",
                "text": "Оказывается, некоторые считают, будто флот России не нужен вовсе. Дескать, для защиты вполне достаточно и сухопутных войск, а захватывать колонии на других континентах Россия не планирует. "
             }
    ]
}